wt_authlib/__init__.py
wt_authlib/errors.py
wt_authlib/fastapi_depends.py
wt_authlib/user_api_client.py
wt_authlib/user_api_settings.py
wt_authlib/user_validator.py
wt_authlib-0.1.6.dist-info/METADATA
wt_authlib-0.1.6.dist-info/WHEEL
wt_authlib-0.1.6.dist-info/top_level.txt
wt_authlib-0.1.6.dist-info/RECORD
