Metadata-Version: 2.4
Name: wt-authlib
Version: 0.1.6
Summary: Librairie d'authentification pour les apis WT
Author-email: David Libert <contact@david.libert.com>
Project-URL: Homepage, https://github.com/dadoo-ai/wt_authlib
Project-URL: Issues, https://github.com/dadoo-ai/wt_authlib/issues
Classifier: Programming Language :: Python :: 3.12
Classifier: Operating System :: OS Independent
Requires-Python: >=3.10
Requires-Dist: fastapi>=0.115.0
Requires-Dist: pyjwt[crypto]>=2.10.1
Requires-Dist: redis>=6.2.0
Requires-Dist: aiohttp>=3.12.13
Requires-Dist: pydantic>=2.11.7
Requires-Dist: python-dotenv>=1.0.0
Requires-Dist: pytest>=8.4.1
Requires-Dist: httpx>=0.28.1
Requires-Dist: pytest-asyncio>=1.1.0
Requires-Dist: build>=1.3.0
Requires-Dist: setuptools>=80.9.0
Requires-Dist: twine>=6.1.0
